omc_rmq/__init__.py
omc_rmq/rmq.py
omc_rmq/binding/__init__.py
omc_rmq/binding/binding.py
omc_rmq/exchange/__init__.py
omc_rmq/exchange/exchange.py
omc_rmq/lib/__init__.py
omc_rmq/lib/formater.py
omc_rmq/lib/rabbitmq.py
omc_rmq/queue/__init__.py
omc_rmq/queue/queue.py
omc_rmq/rmq/__init__.py
omc_rmq/rmq/binding/__init__.py
omc_rmq/rmq/binding/binding.py
omc_rmq/rmq/exchange/__init__.py
omc_rmq/rmq/exchange/exchange.py
omc_rmq/rmq/queue/__init__.py
omc_rmq/rmq/queue/queue.py
omc_rmq/user/__init__.py
omc_rmq/user/user.py
omc_rmq/utils/__init__.py
omc_rmq-0.1.6.dist-info/METADATA
omc_rmq-0.1.6.dist-info/WHEEL
omc_rmq-0.1.6.dist-info/top_level.txt
omc_rmq-0.1.6.dist-info/RECORD
