Metadata-Version: 2.1
Name: omc-rmq
Version: 0.1.6
Summary: command
Home-page: https://github.com/linewx/omc
Author: Lu Ganlin
Author-email: linewx1981@gmail.com
License: MIT
Platform: UNKNOWN
Requires-Dist: omc (>=0.2.1)
